Metadata-Version: 2.4
Name: aiforecast
Version: 0.1.6
Summary: My short description for my project.
Home-page: https://github.com/me/myproject
Author: Awesome Soul
Author-email: 1329152979@qq.com
License: MIT
Classifier: License :: OSI Approved :: MIT License
Classifier: Programming Language :: Python
Classifier: Programming Language :: Python :: 3
Classifier: Programming Language :: Python :: 3.6
Classifier: Programming Language :: Python :: Implementation :: CPython
Classifier: Programming Language :: Python :: Implementation :: PyPy
Requires-Python: >=3.6.0
License-File: LICENSE
Requires-Dist: geopandas>=1.1.1
Requires-Dist: openai>=1.97.0
Requires-Dist: python-dotenv>=1.1.1
Requires-Dist: setuptools>=80.9.0
Dynamic: author
Dynamic: author-email
Dynamic: classifier
Dynamic: description
Dynamic: description-content-type
Dynamic: home-page
Dynamic: license
Dynamic: license-file
Dynamic: requires-dist
Dynamic: requires-python
Dynamic: summary
